wedata/__init__.py
wedata/automl/__init__.py
wedata/automl/h2o.py
wedata/ts_automl/__init__.py
wedata/ts_automl/flaml.py
wedata_automl-0.1.9.post2.dist-info/METADATA
wedata_automl-0.1.9.post2.dist-info/WHEEL
wedata_automl-0.1.9.post2.dist-info/top_level.txt
wedata_automl-0.1.9.post2.dist-info/RECORD
