Metadata-Version: 2.4
Name: wedata-automl
Version: 0.1.9.post2
Summary: AutoML wrapper with integrated MLflow logging, designed in the wedata style.
Home-page: 
Author: maxxhe
License: Apache 2.0
Classifier: Programming Language :: Python :: 3
Classifier: License :: OSI Approved :: Apache Software License
Classifier: Operating System :: OS Independent
Requires-Python: >=3.7
Requires-Dist: h2o_pysparkling_3.5
Requires-Dist: mlflow==2.17.2
Requires-Dist: scikit-learn
Requires-Dist: pandas
Requires-Dist: h2o
Requires-Dist: numpy<2.0
Requires-Dist: flaml[automl,ts_forecast]
Requires-Dist: joblibspark>=0.5.0
Requires-Dist: joblib<=1.3.2
Requires-Dist: optuna
Dynamic: author
Dynamic: classifier
Dynamic: description-content-type
Dynamic: license
Dynamic: requires-dist
Dynamic: requires-python
Dynamic: summary
